mlms/.ipynb_checkpoints/ModelSelection-checkpoint.py
mlms/.ipynb_checkpoints/plot_roc_curve-checkpoint.py
mlms/ModelSelection.py
mlms/__init__.py
mlms/plot_roc_curve.py
mlms-0.11.0.dist-info/METADATA
mlms-0.11.0.dist-info/WHEEL
mlms-0.11.0.dist-info/RECORD
