Metadata-Version: 2.1
Name: mlms
Version: 0.11.0
Summary: This package is to facilitate model selection in Machine Learning.
Home-page: https://github.com/HigherHoopern/ML_ModelSelection
License: MIT
Keywords: Machine Learning,Model Selection
Author: Jason Lu
Author-email: luzhenxian@hotmail.com
Requires-Python: >=3.7,<4.0
Classifier: License :: OSI Approved :: MIT License
Classifier: Programming Language :: Python :: 3
Classifier: Programming Language :: Python :: 3.7
Classifier: Programming Language :: Python :: 3.8
Classifier: Programming Language :: Python :: 3.9
Classifier: Programming Language :: Python :: 3.10
Classifier: Programming Language :: Python :: 3.11
Requires-Dist: pandas (>=1.5.3,<2.0.0)
Requires-Dist: scikit-learn (>=1.2.2,<2.0.0)
Requires-Dist: tqdm (>=4.65.0,<5.0.0)
Requires-Dist: xgboost (>=1.7.4,<2.0.0)
Project-URL: Repository, https://github.com/HigherHoopern/ML_ModelSelection
